confluent_kafka/__init__.py
confluent_kafka/_types.py
confluent_kafka/cimpl.cpython-39-aarch64-linux-gnu.so
confluent_kafka/cimpl.pyi
confluent_kafka/deserializing_consumer.py
confluent_kafka/error.py
confluent_kafka/py.typed
confluent_kafka/serializing_producer.py
confluent_kafka/_model/__init__.py
confluent_kafka/_util/__init__.py
confluent_kafka/_util/conversion_util.py
confluent_kafka/_util/validation_util.py
confluent_kafka/admin/__init__.py
confluent_kafka/admin/_acl.py
confluent_kafka/admin/_cluster.py
confluent_kafka/admin/_config.py
confluent_kafka/admin/_group.py
confluent_kafka/admin/_listoffsets.py
confluent_kafka/admin/_metadata.py
confluent_kafka/admin/_records.py
confluent_kafka/admin/_resource.py
confluent_kafka/admin/_scram.py
confluent_kafka/admin/_topic.py
confluent_kafka/aio/_AIOConsumer.py
confluent_kafka/aio/__init__.py
confluent_kafka/aio/_common.py
confluent_kafka/aio/producer/_AIOProducer.py
confluent_kafka/aio/producer/__init__.py
confluent_kafka/aio/producer/_buffer_timeout_manager.py
confluent_kafka/aio/producer/_kafka_batch_executor.py
confluent_kafka/aio/producer/_message_batch.py
confluent_kafka/aio/producer/_producer_batch_processor.py
confluent_kafka/avro/__init__.py
confluent_kafka/avro/cached_schema_registry_client.py
confluent_kafka/avro/error.py
confluent_kafka/avro/load.py
confluent_kafka/avro/serializer/__init__.py
confluent_kafka/avro/serializer/message_serializer.py
confluent_kafka/kafkatest/__init__.py
confluent_kafka/kafkatest/verifiable_client.py
confluent_kafka/kafkatest/verifiable_consumer.py
confluent_kafka/kafkatest/verifiable_producer.py
confluent_kafka/schema_registry/__init__.py
confluent_kafka/schema_registry/avro.py
confluent_kafka/schema_registry/error.py
confluent_kafka/schema_registry/json_schema.py
confluent_kafka/schema_registry/protobuf.py
confluent_kafka/schema_registry/rule_registry.py
confluent_kafka/schema_registry/schema_registry_client.py
confluent_kafka-2.13.0.dist-info/METADATA
confluent_kafka-2.13.0.dist-info/WHEEL
confluent_kafka-2.13.0.dist-info/top_level.txt
confluent_kafka-2.13.0.dist-info/RECORD
confluent_kafka-2.13.0.dist-info/licenses/LICENSE
