Metadata-Version: 2.1
Name: confluent-kafka
Version: 2.13.0
Summary: Confluent's Python client for Apache Kafka
Author-email: "Confluent Inc." <support@confluent.io>
Project-URL: Homepage, https://github.com/confluentinc/confluent-kafka-python
Classifier: Development Status :: 5 - Production/Stable
Classifier: Intended Audience :: Developers
Classifier: License :: OSI Approved :: Apache Software License
Classifier: Programming Language :: Python
Classifier: Programming Language :: Python :: 3
Classifier: Topic :: Software Development :: Libraries :: Python Modules
Requires-Python: >=3.8
License-File: LICENSE
Provides-Extra: all
Requires-Dist: psutil; extra == "all"
Requires-Dist: opentelemetry-distro; extra == "all"
Requires-Dist: opentelemetry-exporter-otlp; extra == "all"
Requires-Dist: sphinx; extra == "all"
Requires-Dist: sphinx-rtd-theme; extra == "all"
Requires-Dist: pandoc; extra == "all"
Requires-Dist: confluent-kafka; extra == "all"
Requires-Dist: fastapi; extra == "all"
Requires-Dist: pydantic; extra == "all"
Requires-Dist: uvicorn; extra == "all"
Requires-Dist: six; extra == "all"
Requires-Dist: attrs; extra == "all"
Requires-Dist: cachetools; extra == "all"
Requires-Dist: httpx>=0.26; extra == "all"
Requires-Dist: authlib>=1.0.0; extra == "all"
Requires-Dist: requests; extra == "all"
Requires-Dist: avro<2,>=1.11.1; extra == "all"
Requires-Dist: pyrsistent; extra == "all"
Requires-Dist: jsonschema; extra == "all"
Requires-Dist: orjson>=3.10; extra == "all"
Requires-Dist: googleapis-common-protos; extra == "all"
Requires-Dist: protobuf; extra == "all"
Requires-Dist: azure-identity; extra == "all"
Requires-Dist: azure-keyvault-keys; extra == "all"
Requires-Dist: boto3; extra == "all"
Requires-Dist: cel-python>=0.4.0; extra == "all"
Requires-Dist: google-auth; extra == "all"
Requires-Dist: google-api-core; extra == "all"
Requires-Dist: google-cloud-kms; extra == "all"
Requires-Dist: hkdf==0.0.3; extra == "all"
Requires-Dist: hvac; extra == "all"
Requires-Dist: jsonata-python; extra == "all"
Requires-Dist: pyyaml>=6.0.0; extra == "all"
Requires-Dist: tink; extra == "all"
Requires-Dist: urllib3<3; extra == "all"
Requires-Dist: flake8; extra == "all"
Requires-Dist: mypy; extra == "all"
Requires-Dist: types-cachetools; extra == "all"
Requires-Dist: types-requests; extra == "all"
Requires-Dist: orjson; extra == "all"
Requires-Dist: pytest; extra == "all"
Requires-Dist: pytest-timeout; extra == "all"
Requires-Dist: requests-mock; extra == "all"
Requires-Dist: respx; extra == "all"
Requires-Dist: pytest-cov; extra == "all"
Requires-Dist: pluggy<1.6.0; extra == "all"
Requires-Dist: pytest-asyncio; extra == "all"
Requires-Dist: async-timeout; extra == "all"
Requires-Dist: black>=24.0.0; extra == "all"
Requires-Dist: isort>=5.13.0; extra == "all"
Requires-Dist: attrs>=21.2.0; extra == "all"
Requires-Dist: cachetools>=5.5.0; extra == "all"
Requires-Dist: certifi; extra == "all"
Requires-Dist: boto3>=1.35; extra == "all"
Requires-Dist: google-re2<1.1.20251105; extra == "all"
Requires-Dist: tomli; python_version < "3.11" and extra == "all"
Requires-Dist: fastavro<1.8.0,>=1.5.4; python_version == "3.7" and extra == "all"
Requires-Dist: fastavro<2,>=1.5.4; python_version > "3.7" and extra == "all"
Provides-Extra: avro
Requires-Dist: requests; extra == "avro"
Requires-Dist: avro<2,>=1.11.1; extra == "avro"
Requires-Dist: attrs>=21.2.0; extra == "avro"
Requires-Dist: cachetools>=5.5.0; extra == "avro"
Requires-Dist: certifi; extra == "avro"
Requires-Dist: httpx>=0.26; extra == "avro"
Requires-Dist: authlib>=1.0.0; extra == "avro"
Requires-Dist: fastavro<1.8.0,>=1.5.4; python_version == "3.7" and extra == "avro"
Requires-Dist: fastavro<2,>=1.5.4; python_version > "3.7" and extra == "avro"
Provides-Extra: dev
Requires-Dist: sphinx; extra == "dev"
Requires-Dist: sphinx-rtd-theme; extra == "dev"
Requires-Dist: pandoc; extra == "dev"
Requires-Dist: confluent-kafka; extra == "dev"
Requires-Dist: fastapi; extra == "dev"
Requires-Dist: pydantic; extra == "dev"
Requires-Dist: uvicorn; extra == "dev"
Requires-Dist: six; extra == "dev"
Requires-Dist: attrs; extra == "dev"
Requires-Dist: cachetools; extra == "dev"
Requires-Dist: httpx>=0.26; extra == "dev"
Requires-Dist: authlib>=1.0.0; extra == "dev"
Requires-Dist: requests; extra == "dev"
Requires-Dist: avro<2,>=1.11.1; extra == "dev"
Requires-Dist: pyrsistent; extra == "dev"
Requires-Dist: jsonschema; extra == "dev"
Requires-Dist: orjson>=3.10; extra == "dev"
Requires-Dist: googleapis-common-protos; extra == "dev"
Requires-Dist: protobuf; extra == "dev"
Requires-Dist: azure-identity; extra == "dev"
Requires-Dist: azure-keyvault-keys; extra == "dev"
Requires-Dist: boto3; extra == "dev"
Requires-Dist: cel-python>=0.4.0; extra == "dev"
Requires-Dist: google-auth; extra == "dev"
Requires-Dist: google-api-core; extra == "dev"
Requires-Dist: google-cloud-kms; extra == "dev"
Requires-Dist: hkdf==0.0.3; extra == "dev"
Requires-Dist: hvac; extra == "dev"
Requires-Dist: jsonata-python; extra == "dev"
Requires-Dist: pyyaml>=6.0.0; extra == "dev"
Requires-Dist: tink; extra == "dev"
Requires-Dist: urllib3<3; extra == "dev"
Requires-Dist: flake8; extra == "dev"
Requires-Dist: mypy; extra == "dev"
Requires-Dist: types-cachetools; extra == "dev"
Requires-Dist: types-requests; extra == "dev"
Requires-Dist: orjson; extra == "dev"
Requires-Dist: pytest; extra == "dev"
Requires-Dist: pytest-timeout; extra == "dev"
Requires-Dist: requests-mock; extra == "dev"
Requires-Dist: respx; extra == "dev"
Requires-Dist: pytest-cov; extra == "dev"
Requires-Dist: pluggy<1.6.0; extra == "dev"
Requires-Dist: pytest-asyncio; extra == "dev"
Requires-Dist: async-timeout; extra == "dev"
Requires-Dist: black>=24.0.0; extra == "dev"
Requires-Dist: isort>=5.13.0; extra == "dev"
Requires-Dist: attrs>=21.2.0; extra == "dev"
Requires-Dist: cachetools>=5.5.0; extra == "dev"
Requires-Dist: certifi; extra == "dev"
Requires-Dist: boto3>=1.35; extra == "dev"
Requires-Dist: google-re2<1.1.20251105; extra == "dev"
Requires-Dist: tomli; python_version < "3.11" and extra == "dev"
Requires-Dist: fastavro<1.8.0,>=1.5.4; python_version == "3.7" and extra == "dev"
Requires-Dist: fastavro<2,>=1.5.4; python_version > "3.7" and extra == "dev"
Provides-Extra: docs
Requires-Dist: sphinx; extra == "docs"
Requires-Dist: sphinx-rtd-theme; extra == "docs"
Requires-Dist: pandoc; extra == "docs"
Requires-Dist: attrs>=21.2.0; extra == "docs"
Requires-Dist: cachetools>=5.5.0; extra == "docs"
Requires-Dist: certifi; extra == "docs"
Requires-Dist: httpx>=0.26; extra == "docs"
Requires-Dist: authlib>=1.0.0; extra == "docs"
Requires-Dist: azure-identity; extra == "docs"
Requires-Dist: azure-keyvault-keys; extra == "docs"
Requires-Dist: boto3>=1.35; extra == "docs"
Requires-Dist: cel-python>=0.4.0; extra == "docs"
Requires-Dist: google-re2<1.1.20251105; extra == "docs"
Requires-Dist: google-auth; extra == "docs"
Requires-Dist: google-api-core; extra == "docs"
Requires-Dist: google-cloud-kms; extra == "docs"
Requires-Dist: hkdf==0.0.3; extra == "docs"
Requires-Dist: hvac; extra == "docs"
Requires-Dist: jsonata-python; extra == "docs"
Requires-Dist: pyyaml>=6.0.0; extra == "docs"
Requires-Dist: tink; extra == "docs"
Requires-Dist: requests; extra == "docs"
Requires-Dist: avro<2,>=1.11.1; extra == "docs"
Requires-Dist: pyrsistent; extra == "docs"
Requires-Dist: jsonschema; extra == "docs"
Requires-Dist: orjson>=3.10; extra == "docs"
Requires-Dist: googleapis-common-protos; extra == "docs"
Requires-Dist: protobuf; extra == "docs"
Requires-Dist: tomli; python_version < "3.11" and extra == "docs"
Requires-Dist: fastavro<1.8.0,>=1.5.4; python_version == "3.7" and extra == "docs"
Requires-Dist: fastavro<2,>=1.5.4; python_version > "3.7" and extra == "docs"
Provides-Extra: examples
Requires-Dist: confluent-kafka; extra == "examples"
Requires-Dist: fastapi; extra == "examples"
Requires-Dist: pydantic; extra == "examples"
Requires-Dist: uvicorn; extra == "examples"
Requires-Dist: six; extra == "examples"
Requires-Dist: attrs; extra == "examples"
Requires-Dist: cachetools; extra == "examples"
Requires-Dist: httpx>=0.26; extra == "examples"
Requires-Dist: authlib>=1.0.0; extra == "examples"
Requires-Dist: requests; extra == "examples"
Requires-Dist: avro<2,>=1.11.1; extra == "examples"
Requires-Dist: pyrsistent; extra == "examples"
Requires-Dist: jsonschema; extra == "examples"
Requires-Dist: orjson>=3.10; extra == "examples"
Requires-Dist: googleapis-common-protos; extra == "examples"
Requires-Dist: protobuf; extra == "examples"
Requires-Dist: azure-identity; extra == "examples"
Requires-Dist: azure-keyvault-keys; extra == "examples"
Requires-Dist: boto3; extra == "examples"
Requires-Dist: cel-python>=0.4.0; extra == "examples"
Requires-Dist: google-auth; extra == "examples"
Requires-Dist: google-api-core; extra == "examples"
Requires-Dist: google-cloud-kms; extra == "examples"
Requires-Dist: hkdf==0.0.3; extra == "examples"
Requires-Dist: hvac; extra == "examples"
Requires-Dist: jsonata-python; extra == "examples"
Requires-Dist: pyyaml>=6.0.0; extra == "examples"
Requires-Dist: tink; extra == "examples"
Requires-Dist: fastavro<1.8.0,>=1.5.4; python_version == "3.7" and extra == "examples"
Requires-Dist: fastavro<2,>=1.5.4; python_version > "3.7" and extra == "examples"
Provides-Extra: json
Requires-Dist: pyrsistent; extra == "json"
Requires-Dist: jsonschema; extra == "json"
Requires-Dist: orjson>=3.10; extra == "json"
Requires-Dist: attrs>=21.2.0; extra == "json"
Requires-Dist: cachetools>=5.5.0; extra == "json"
Requires-Dist: certifi; extra == "json"
Requires-Dist: httpx>=0.26; extra == "json"
Requires-Dist: authlib>=1.0.0; extra == "json"
Provides-Extra: protobuf
Requires-Dist: googleapis-common-protos; extra == "protobuf"
Requires-Dist: protobuf; extra == "protobuf"
Requires-Dist: attrs>=21.2.0; extra == "protobuf"
Requires-Dist: cachetools>=5.5.0; extra == "protobuf"
Requires-Dist: certifi; extra == "protobuf"
Requires-Dist: httpx>=0.26; extra == "protobuf"
Requires-Dist: authlib>=1.0.0; extra == "protobuf"
Provides-Extra: rules
Requires-Dist: azure-identity; extra == "rules"
Requires-Dist: azure-keyvault-keys; extra == "rules"
Requires-Dist: boto3>=1.35; extra == "rules"
Requires-Dist: cel-python>=0.4.0; extra == "rules"
Requires-Dist: google-re2<1.1.20251105; extra == "rules"
Requires-Dist: google-auth; extra == "rules"
Requires-Dist: google-api-core; extra == "rules"
Requires-Dist: google-cloud-kms; extra == "rules"
Requires-Dist: hkdf==0.0.3; extra == "rules"
Requires-Dist: hvac; extra == "rules"
Requires-Dist: jsonata-python; extra == "rules"
Requires-Dist: pyyaml>=6.0.0; extra == "rules"
Requires-Dist: tink; extra == "rules"
Requires-Dist: attrs>=21.2.0; extra == "rules"
Requires-Dist: cachetools>=5.5.0; extra == "rules"
Requires-Dist: certifi; extra == "rules"
Requires-Dist: httpx>=0.26; extra == "rules"
Requires-Dist: authlib>=1.0.0; extra == "rules"
Provides-Extra: schema_registry
Requires-Dist: attrs>=21.2.0; extra == "schema-registry"
Requires-Dist: cachetools>=5.5.0; extra == "schema-registry"
Requires-Dist: certifi; extra == "schema-registry"
Requires-Dist: httpx>=0.26; extra == "schema-registry"
Requires-Dist: authlib>=1.0.0; extra == "schema-registry"
Provides-Extra: schemaregistry
Requires-Dist: attrs>=21.2.0; extra == "schemaregistry"
Requires-Dist: cachetools>=5.5.0; extra == "schemaregistry"
Requires-Dist: certifi; extra == "schemaregistry"
Requires-Dist: httpx>=0.26; extra == "schemaregistry"
Requires-Dist: authlib>=1.0.0; extra == "schemaregistry"
Provides-Extra: soaktest
Requires-Dist: psutil; extra == "soaktest"
Requires-Dist: opentelemetry-distro; extra == "soaktest"
Requires-Dist: opentelemetry-exporter-otlp; extra == "soaktest"
Provides-Extra: tests
Requires-Dist: urllib3<3; extra == "tests"
Requires-Dist: flake8; extra == "tests"
Requires-Dist: mypy; extra == "tests"
Requires-Dist: attrs; extra == "tests"
Requires-Dist: types-cachetools; extra == "tests"
Requires-Dist: types-requests; extra == "tests"
Requires-Dist: orjson; extra == "tests"
Requires-Dist: pytest; extra == "tests"
Requires-Dist: pytest-timeout; extra == "tests"
Requires-Dist: requests-mock; extra == "tests"
Requires-Dist: respx; extra == "tests"
Requires-Dist: pytest-cov; extra == "tests"
Requires-Dist: pluggy<1.6.0; extra == "tests"
Requires-Dist: pytest-asyncio; extra == "tests"
Requires-Dist: async-timeout; extra == "tests"
Requires-Dist: black>=24.0.0; extra == "tests"
Requires-Dist: isort>=5.13.0; extra == "tests"
Requires-Dist: attrs>=21.2.0; extra == "tests"
Requires-Dist: cachetools>=5.5.0; extra == "tests"
Requires-Dist: certifi; extra == "tests"
Requires-Dist: httpx>=0.26; extra == "tests"
Requires-Dist: authlib>=1.0.0; extra == "tests"
Requires-Dist: azure-identity; extra == "tests"
Requires-Dist: azure-keyvault-keys; extra == "tests"
Requires-Dist: boto3>=1.35; extra == "tests"
Requires-Dist: cel-python>=0.4.0; extra == "tests"
Requires-Dist: google-re2<1.1.20251105; extra == "tests"
Requires-Dist: google-auth; extra == "tests"
Requires-Dist: google-api-core; extra == "tests"
Requires-Dist: google-cloud-kms; extra == "tests"
Requires-Dist: hkdf==0.0.3; extra == "tests"
Requires-Dist: hvac; extra == "tests"
Requires-Dist: jsonata-python; extra == "tests"
Requires-Dist: pyyaml>=6.0.0; extra == "tests"
Requires-Dist: tink; extra == "tests"
Requires-Dist: requests; extra == "tests"
Requires-Dist: avro<2,>=1.11.1; extra == "tests"
Requires-Dist: pyrsistent; extra == "tests"
Requires-Dist: jsonschema; extra == "tests"
Requires-Dist: orjson>=3.10; extra == "tests"
Requires-Dist: googleapis-common-protos; extra == "tests"
Requires-Dist: protobuf; extra == "tests"
Requires-Dist: fastavro<1.8.0,>=1.5.4; python_version == "3.7" and extra == "tests"
Requires-Dist: fastavro<2,>=1.5.4; python_version > "3.7" and extra == "tests"
